qlacref_authorities/__init__.py
qlacref_authorities/records.json
quality_lac_data_ref_authorities-2021.4.dist-info/LICENSE.txt
quality_lac_data_ref_authorities-2021.4.dist-info/WHEEL
quality_lac_data_ref_authorities-2021.4.dist-info/METADATA
quality_lac_data_ref_authorities-2021.4.dist-info/RECORD
